LICENSE
MANIFEST.in
README.md
setup.cfg
setup.py
stdeb.cfg
./aehostd/__about__.py
./aehostd/__init__.py
./aehostd/base.py
./aehostd/cfg.py
./aehostd/config.py
./aehostd/group.py
./aehostd/hosts.py
./aehostd/ldapconn.py
./aehostd/log.py
./aehostd/monitor.py
./aehostd/pam.py
./aehostd/passwd.py
./aehostd/priv.py
./aehostd/refresh.py
./aehostd/req.py
./aehostd/service.py
./aehostd/srv.py
aehostd.egg-info/PKG-INFO
aehostd.egg-info/SOURCES.txt
aehostd.egg-info/dependency_links.txt
aehostd.egg-info/entry_points.txt
aehostd.egg-info/not-zip-safe
aehostd.egg-info/requires.txt
aehostd.egg-info/top_level.txt