Metadata-Version: 2.1
Name: aehostd
Version: 1.5.12
Summary: AE-DIR host demon
Home-page: https://ae-dir.com/aehostd.html
Download-URL: https://pypi.org/project/aehostd/#files
Author: Michael Stroeder
Author-email: michael@stroeder.com
Maintainer: Michael Stroeder
Maintainer-email: michael@stroeder.com
License: Apache-2.0
Project-URL: Code, https://code.stroeder.com/AE-DIR/aehostd
Project-URL: Issue tracker, https://code.stroeder.com/AE-DIR/aehostd/issues
Keywords: LDAP,LDAPv3,OpenLDAP,Æ-DIR,AE-DIR
Classifier: Development Status :: 5 - Production/Stable
Classifier: Environment :: No Input/Output (Daemon)
Classifier: Intended Audience :: Information Technology
Classifier: Intended Audience :: System Administrators
Classifier: License :: OSI Approved :: Apache Software License
Classifier: Operating System :: POSIX
Classifier: Operating System :: POSIX :: Linux
Classifier: Operating System :: Unix
Classifier: Programming Language :: Python
Classifier: Programming Language :: Python :: 3
Classifier: Programming Language :: Python :: 3.6
Classifier: Programming Language :: Python :: 3.7
Classifier: Programming Language :: Python :: 3.8
Classifier: Programming Language :: Python :: 3.9
Classifier: Programming Language :: Python :: 3.10
Classifier: Programming Language :: Python :: 3 :: Only
Classifier: Topic :: System :: Systems Administration
Classifier: Topic :: System :: Systems Administration :: Authentication/Directory
Classifier: Topic :: System :: Systems Administration :: Authentication/Directory :: LDAP
Requires-Python: >=3.6
License-File: LICENSE
